[{"sloka":"[Sita permits Hanuman to depart]ஷ்ருத்வா து வசநஂ தஸ்ய வாயுஸூநோர்மஹாத்மநஃ.உவாசாத்மஹிதஂ வாக்யஂ ஸீதா ஸுரஸுதோபமா৷৷5.40.1৷৷"},{"sloka":"த்வாஂ தரிஷ்ட்வா ப்ரியவக்தாரஂ ஸம்ப்ரஹரிஷ்யாமி வாநரஃ.அர்தஸஞ்ஜாதஸஸ்யேவ வரிஷ்டிஂ ப்ராப்ய வஸுந்தரா৷৷5.40.2৷৷"},{"sloka":"யதா தஂ புருஷவ்யாக்ரஂ காத்ரைஷ்ஷோகாபிகர்ஷிதைஃ.ஸஂஸ்பரிஷேயஂ ஸகாமாஹஂ ததா குரு தயாஂ மயி৷৷5.40.3৷৷"},{"sloka":"அபிஜ்ஞாநஂ ச ராமஸ்ய தத்யா ஹரிகணோத்தம.க்ஷிப்தாமிஷீகாஂ காகஸ்ய கோபாதேகாக்ஷிஷாதநீம்৷৷5.40.4৷৷"},{"sloka":"மநஷ்ஷிலாயாஸ்திலகோ கண்டபார்ஷ்வே நிவேஷிதஃ.த்வயா ப்ரணஷ்டே திலகே தஂ கில ஸ்மர்துமர்ஹஸி৷৷5.40.5৷৷"},{"sloka":"ஸ வீர்யவாந்கதஂ ஸீதாஂ ஹரிதாஂ ஸமநுமந்யஸே.வஸந்தீஂ ரக்ஷஸாஂ மத்யே மஹேந்த்ரவருணோபமஃ৷৷5.40.6৷৷"},{"sloka":"ஏஷ சூடாமணிர்திவ்யோ மயா ஸுபரிரக்ஷிதஃ.ஏதஂ தரிஷ்ட்வா ப்ரஹரிஷ்யாமி வ்யஸநே த்வாமிவாநக৷৷5.40.7৷৷"},{"sloka":"ஏஷ நிர்யாதிதஷ்ஷ்ரீமாந்மயா தே வாரிஸம்பவஃ.அதஃ பரஂ ந ஷக்ஷ்யாமி ஜீவிதுஂ ஷோகலாலஸா৷৷5.40.8৷৷"},{"sloka":"அஸஹ்யாநி ச துஃகாநி வாசஷ்ச ஹரிதயச்சிதஃ.ராக்ஷஸீநாஂ ஸுகோராணாஂ த்வத்கரிதே மர்ஷயாம்யஹம்৷৷5.40.9৷৷"},{"sloka":"தாரயிஷ்யாமி மாஸஂ து ஜீவிதஂ ஷத்ருஸூதந.ஊர்த்வஂ மாஸாந்ந ஜீவிஷ்யே த்வயா ஹீநா நரிபாத்மஜ৷৷5.40.10৷৷"},{"sloka":"கோரோ ராக்ஷஸராஜோயஂ தரிஷ்டிஷ்ச ந ஸுகா மயி.த்வாஂ ச ஷ்ருத்வா விபத்யந்தஂ ந ஜீவேயமஹஂ க்ஷணம்৷৷5.40.11৷৷"},{"sloka":"வைதேஹ்யா வசநஂ ஷ்ருத்வா கருணஂ ஸாஷ்ரு பாஷிதம்.அதாப்ரவீந்மஹாதேஜா ஹநுமாந்மாருதாத்மஜஃ৷৷5.40.12৷৷"},{"sloka":"த்வச்சோகவிமுகோ ராமோ தேவி ஸத்யேந தே ஷபே.ராமே துஃகாபிபூதே து லக்ஷ்மணஃ பரிதப்யதே৷৷5.40.13৷৷"},{"sloka":"கதஞ்சித்பவதீ தரிஷ்டா ந காலஃ பரிஷோசிதும்.இமஂ முஹூர்தஂ துஃகாநாமந்தஂ த்ரக்ஷ்யஸி பாமிநி৷৷5.40.14৷৷"},{"sloka":"தாவுபௌ புருஷவ்யாக்ரௌ ராஜபுத்ராவரிந்தமௌ.த்வத்தர்ஷநகரிதோத்ஸாஹௌ லங்காஂ பஸ்மீகரிஷ்யதஃ৷৷5.40.15৷৷"},{"sloka":"ஹத்த்வா ச ஸமரே க்ரூரஂ ராவணஂ ஸஹபாந்தவம்.ராகவௌ த்வாஂ விஷாலாக்ஷி ஸ்வாஂ புரீஂ ப்ராபயிஷ்யதஃ৷৷5.40.16৷৷"},{"sloka":"யத்து ராமோ விஜாநீயாதபிஜ்ஞாநமநிந்திதே.ப்ரீதிஸஞ்ஜநநஂ தஸ்ய பூயஸ்த்வஂ தாதுமர்ஹஸி৷৷5.40.17৷৷"},{"sloka":"ஸாப்ரவீத்தத்தமேவேதி மயாபிஜ்ஞாநமுத்தமம்.ஏததேவ ஹி ராமஸ்ய தரிஷ்ட்வா மத்கேஷபூஷணம்৷৷5.40.18৷৷ஷ்ரத்தேயஂ ஹநுமந்வாக்யஂ தவ வீர பவிஷ்யதி."},{"sloka":"ஸ தஂ மணிவரஂ கரிஹ்ய ஷ்ரீமாந்ப்லவகஸத்தமஃ৷৷5.40.19৷৷ப்ரணம்ய ஷிரஸா தேவீஂ கமநாயோபசக்ரமே."},{"sloka":"தமுத்பாதகரிதோத்ஸாஹமவேக்ஷ்ய ஹரிபுங்கவம்৷৷5.40.20৷৷வர்தமாநஂ மஹாவேகமுவாச ஜநகாத்மஜா.அஷ்ருபூர்ணமுகீ தீநா பாஷ்பகத்கதயா கிரா৷৷5.40.21৷৷"},{"sloka":"ஹநுமந்ஸிஂஹஸங்காஷௌ ப்ராதரௌ ராமலக்ஷ்மணௌ.ஸுக்ரீவஂ ச ஸஹாமாத்யஂ ஸர்வாந் ப்ரூயாஹ்யநாமயம்৷৷5.40.22৷৷"},{"sloka":"யதா ச ஸ மஹாபாஹுர்மாஂ தாரயதி ராகவஃ.அஸ்மாத்து:காம்புஸம்ரோதாத்த்வஂ ஸமாதாதுமர்ஹஸி৷৷5.40.23৷৷"},{"sloka":"இமஂ ச தீவ்ரஂ மம ஷோகவேகஂ ரக்ஷோபிரேபிஃ பரிபர்த்ஸநஂ ச.ப்ரூயாஸ்து ராமஸ்ய கதஸ்ஸமீபம் ஷிவஷ்ச தேத்வாஸ்து ஹரிப்ரவீர৷৷5.40.24৷৷"},{"sloka":"ஸ ராஜபுத்ர்ய்ராப்ரதிவேதிதார்தஃ கபிஃ கரிதார்தஃ பரிஹரிஷ்டசேதாஃ.அல்பாவஷேஷஂ ப்ரஸமீக்ஷ்ய கார்யஂ திஷஂ ஹ்யுதீசீஂ மநஸா ஜகாம৷৷5.40.25৷৷"},{"sloka":"[Sita permits Hanuman to depart]ஷ்ருத்வா து வசநஂ தஸ்ய வாயுஸூநோர்மஹாத்மநஃ.உவாசாத்மஹிதஂ வாக்யஂ ஸீதா ஸுரஸுதோபமா৷৷5.40.1৷৷"},{"sloka":"த்வாஂ தரிஷ்ட்வா ப்ரியவக்தாரஂ ஸம்ப்ரஹரிஷ்யாமி வாநரஃ.அர்தஸஞ்ஜாதஸஸ்யேவ வரிஷ்டிஂ ப்ராப்ய வஸுந்தரா৷৷5.40.2৷৷"},{"sloka":"யதா தஂ புருஷவ்யாக்ரஂ காத்ரைஷ்ஷோகாபிகர்ஷிதைஃ.ஸஂஸ்பரிஷேயஂ ஸகாமாஹஂ ததா குரு தயாஂ மயி৷৷5.40.3৷৷"},{"sloka":"அபிஜ்ஞாநஂ ச ராமஸ்ய தத்யா ஹரிகணோத்தம.க்ஷிப்தாமிஷீகாஂ காகஸ்ய கோபாதேகாக்ஷிஷாதநீம்৷৷5.40.4৷৷"},{"sloka":"மநஷ்ஷிலாயாஸ்திலகோ கண்டபார்ஷ்வே நிவேஷிதஃ.த்வயா ப்ரணஷ்டே திலகே தஂ கில ஸ்மர்துமர்ஹஸி৷৷5.40.5৷৷"},{"sloka":"ஸ வீர்யவாந்கதஂ ஸீதாஂ ஹரிதாஂ ஸமநுமந்யஸே.வஸந்தீஂ ரக்ஷஸாஂ மத்யே மஹேந்த்ரவருணோபமஃ৷৷5.40.6৷৷"},{"sloka":"ஏஷ சூடாமணிர்திவ்யோ மயா ஸுபரிரக்ஷிதஃ.ஏதஂ தரிஷ்ட்வா ப்ரஹரிஷ்யாமி வ்யஸநே த்வாமிவாநக৷৷5.40.7৷৷"},{"sloka":"ஏஷ நிர்யாதிதஷ்ஷ்ரீமாந்மயா தே வாரிஸம்பவஃ.அதஃ பரஂ ந ஷக்ஷ்யாமி ஜீவிதுஂ ஷோகலாலஸா৷৷5.40.8৷৷"},{"sloka":"அஸஹ்யாநி ச துஃகாநி வாசஷ்ச ஹரிதயச்சிதஃ.ராக்ஷஸீநாஂ ஸுகோராணாஂ த்வத்கரிதே மர்ஷயாம்யஹம்৷৷5.40.9৷৷"},{"sloka":"தாரயிஷ்யாமி மாஸஂ து ஜீவிதஂ ஷத்ருஸூதந.ஊர்த்வஂ மாஸாந்ந ஜீவிஷ்யே த்வயா ஹீநா நரிபாத்மஜ৷৷5.40.10৷৷"},{"sloka":"கோரோ ராக்ஷஸராஜோயஂ தரிஷ்டிஷ்ச ந ஸுகா மயி.த்வாஂ ச ஷ்ருத்வா விபத்யந்தஂ ந ஜீவேயமஹஂ க்ஷணம்৷৷5.40.11৷৷"},{"sloka":"வைதேஹ்யா வசநஂ ஷ்ருத்வா கருணஂ ஸாஷ்ரு பாஷிதம்.அதாப்ரவீந்மஹாதேஜா ஹநுமாந்மாருதாத்மஜஃ৷৷5.40.12৷৷"},{"sloka":"த்வச்சோகவிமுகோ ராமோ தேவி ஸத்யேந தே ஷபே.ராமே துஃகாபிபூதே து லக்ஷ்மணஃ பரிதப்யதே৷৷5.40.13৷৷"},{"sloka":"கதஞ்சித்பவதீ தரிஷ்டா ந காலஃ பரிஷோசிதும்.இமஂ முஹூர்தஂ துஃகாநாமந்தஂ த்ரக்ஷ்யஸி பாமிநி৷৷5.40.14৷৷"},{"sloka":"தாவுபௌ புருஷவ்யாக்ரௌ ராஜபுத்ராவரிந்தமௌ.த்வத்தர்ஷநகரிதோத்ஸாஹௌ லங்காஂ பஸ்மீகரிஷ்யதஃ৷৷5.40.15৷৷"},{"sloka":"ஹத்த்வா ச ஸமரே க்ரூரஂ ராவணஂ ஸஹபாந்தவம்.ராகவௌ த்வாஂ விஷாலாக்ஷி ஸ்வாஂ புரீஂ ப்ராபயிஷ்யதஃ৷৷5.40.16৷৷"},{"sloka":"யத்து ராமோ விஜாநீயாதபிஜ்ஞாநமநிந்திதே.ப்ரீதிஸஞ்ஜநநஂ தஸ்ய பூயஸ்த்வஂ தாதுமர்ஹஸி৷৷5.40.17৷৷"},{"sloka":"ஸாப்ரவீத்தத்தமேவேதி மயாபிஜ்ஞாநமுத்தமம்.ஏததேவ ஹி ராமஸ்ய தரிஷ்ட்வா மத்கேஷபூஷணம்৷৷5.40.18৷৷ஷ்ரத்தேயஂ ஹநுமந்வாக்யஂ தவ வீர பவிஷ்யதி."},{"sloka":"ஸ தஂ மணிவரஂ கரிஹ்ய ஷ்ரீமாந்ப்லவகஸத்தமஃ৷৷5.40.19৷৷ப்ரணம்ய ஷிரஸா தேவீஂ கமநாயோபசக்ரமே."},{"sloka":"தமுத்பாதகரிதோத்ஸாஹமவேக்ஷ்ய ஹரிபுங்கவம்৷৷5.40.20৷৷வர்தமாநஂ மஹாவேகமுவாச ஜநகாத்மஜா.அஷ்ருபூர்ணமுகீ தீநா பாஷ்பகத்கதயா கிரா৷৷5.40.21৷৷"},{"sloka":"ஹநுமந்ஸிஂஹஸங்காஷௌ ப்ராதரௌ ராமலக்ஷ்மணௌ.ஸுக்ரீவஂ ச ஸஹாமாத்யஂ ஸர்வாந் ப்ரூயாஹ்யநாமயம்৷৷5.40.22৷৷"},{"sloka":"யதா ச ஸ மஹாபாஹுர்மாஂ தாரயதி ராகவஃ.அஸ்மாத்து:காம்புஸம்ரோதாத்த்வஂ ஸமாதாதுமர்ஹஸி৷৷5.40.23৷৷"},{"sloka":"இமஂ ச தீவ்ரஂ மம ஷோகவேகஂ ரக்ஷோபிரேபிஃ பரிபர்த்ஸநஂ ச.ப்ரூயாஸ்து ராமஸ்ய கதஸ்ஸமீபம் ஷிவஷ்ச தேத்வாஸ்து ஹரிப்ரவீர৷৷5.40.24৷৷"},{"sloka":"ஸ ராஜபுத்ர்ய்ராப்ரதிவேதிதார்தஃ கபிஃ கரிதார்தஃ பரிஹரிஷ்டசேதாஃ.அல்பாவஷேஷஂ ப்ரஸமீக்ஷ்ய கார்யஂ திஷஂ ஹ்யுதீசீஂ மநஸா ஜகாம৷৷5.40.25৷৷"}]