[{"sloka":"[Hanuman sings the story of glory of Rama within Sita's hearing.]ஏவஂ பஹுவிதாஂ சிந்தாஂ சிந்தயித்வா மஹாகபிஃ.ஸஂஷ்ரவே மதுரஂ வாக்யஂ வைதேஹ்யா வ்யாஜஹார ஹ৷৷5.31.1৷৷"},{"sloka":"ராஜா தஷரதோ நாம ரதகுஞ்ஜரவாஜிமாந்.புண்யஷீலோ மஹாகீர்திரிக்ஷ்வாகூணாஂ மஹாயஷாஃ৷৷5.31.2৷৷"},{"sloka":"ராஜர்ஷீணாஂ குணஷ்ரேஷ்டஸ்தபஸா சர்ஷிபி ஸ்ஸமஃ.சக்ரவர்திகுலே ஜாதஃ புரந்தரஸமோ பலே৷৷5.31.3৷৷"},{"sloka":"அஹிஂஸாரதிரக்ஷுத்ரோ கரிணீ ஸத்யபராக்ரமஃ.முக்யஷ்சேக்ஷ்வாகுவஂஷஸ்ய லக்ஷ்மீவாந் லக்ஷ்மிவர்தநஃ৷৷5.31.4৷৷"},{"sloka":"பார்திவவ்யஞ்ஜநைர்யுக்தஃ பரிதுஷ்ரீஃ பார்திவர்ஷபஃ.பரிதிவ்யாஂ சதுரந்தாயாஂ விஷ்ருதஸ்ஸுகதஸ்ஸுகீ৷৷5.31.5৷৷"},{"sloka":"தஸ்ய புத்ரஃ ப்ரியோ ஜ்யேஷ்டஸ்தாராதிபநிபாநநஃ.ராமோ நாம விஷேஷஜ்ஞஃ ஷ்ரேஷ்ட ஸ்ஸர்வதநுஷ்மதாம்৷৷5.31.6৷৷"},{"sloka":"ரக்ஷிதா ஸ்வஸ்ய தர்மஸ்ய ஸ்வஜநஸ்ய ச ரக்ஷிதா.ரக்ஷிதா ஜீவலோகஸ்ய தர்மஸ்ய ச பரந்தபஃ৷৷5.31.7৷৷"},{"sloka":"தஸ்ய ஸத்யாபிஸந்தஸ்ய வரித்தஸ்ய வசநாத்பிதுஃ.ஸபார்யஸ்ஸஹ ச ப்ராத்ரா வீரஃ ப்ரவ்ராஜிதோ வநம்৷৷5.31.8৷৷"},{"sloka":"தேந தத்ர மஹாரண்யே மரிகயாஂ பரிதாவதா.ராக்ஷஸா நிஹதாஷ்ஷூரா பஹவஃ காமரூபிணஃ৷৷5.31.9৷৷"},{"sloka":"ஜநஸ்தாநவதஂ ஷ்ருத்வா ஹதௌ ச கரதூஷணௌ.ததஸ்த்வமர்ஷாபஹரிதா ஜாநகீ ராவணேந து৷৷5.31.10৷৷வஞ்சயித்வா வநே ராமஂ மரிகரூபேண மாயயா."},{"sloka":"ஸ மார்கமாணஸ்தாஂ தேவீஂ ராமஸ்ஸீதாமநிந்திதாம்৷৷5.31.11৷৷ஆஸஸாத வநே மித்ரஂ ஸுக்ரீவஂ நாம வாநரம்."},{"sloka":"தத ஸ்ஸ வாலிநஂ ஹத்வா ராமஃ பரபுரஞ்ஜயஃ৷৷5.31.12৷৷ப்ராயச்சத்கபிராஜ்யஂ தத்ஸுக்ரீவாய மஹாபலஃ."},{"sloka":"ஸுக்ரீவேணாபி ஸந்திஷ்டா ஹரயஃ காமரூபிணஃ৷৷5.31.13৷৷திக்ஷு ஸர்வாஸு தாஂ தேவீஂ விசிந்வந்தி ஸஹஸ்ரஷஃ."},{"sloka":"அஹஂ ஸம்பாதிவசநாச்சதயோஜநமாயதம்৷৷5.31.14৷৷அஸ்யா ஹேதோர்விஷாலாக்ஷ்யாஃ ஸாகரஂ வேகவாந்ப்லுதஃ."},{"sloka":"யதாரூபாஂ யதாவர்ணாஂ யதாலக்ஷ்மீவதீஂ ச நிஷ்சிதாம்৷৷5.31.15৷৷அஷ்ரௌஷஂ ராகவஸ்யாஹஂ ஸேயமாஸாதிதா மயா."},{"sloka":"விரராமைவமுக்த்வாஸௌ வாசஂ வாநரபுங்கவஃ৷৷5.31.16৷৷ஜாநகீ சாபி தச்ச்ருத்வா பரஂ விஸ்மயமாகதா."},{"sloka":"ததஸ்ஸா வக்ரகேஷாந்தா ஸுகேஷீ கேஷஸஂவரிதம்৷৷5.31.17৷৷உந்நம்ய வதநஂ பீருஷ்ஷிஂஷுபாவரிக்ஷமைக்ஷத."},{"sloka":"நிஷம்ய ஸீதா வசநஂ கபேஷ்ச திஷஷ்ச ஸர்வாஃ ப்ரதிஷஷ்ச வீக்ஷ்ய.ஸ்வயஂ ப்ரஹர்ஷஂ பரமஂ ஜகாம ஸர்வாத்மநா ராமமநுஸ்மரந்தீ ৷৷5.31.18৷৷"},{"sloka":"ஸா திர்யகூர்த்வஂ ச ததாப்யதஸ்தாந்நிரீக்ஷமாணா தமசிந்த்யபுத்திம்.ததர்ஷ பிங்காதிபதேரமாத்யஂ வாதாத்மஜஂ ஸூர்யமிவோதயஸ்தம்৷৷5.31.19৷৷"},{"sloka":"[Hanuman sings the story of glory of Rama within Sita's hearing.]ஏவஂ பஹுவிதாஂ சிந்தாஂ சிந்தயித்வா மஹாகபிஃ.ஸஂஷ்ரவே மதுரஂ வாக்யஂ வைதேஹ்யா வ்யாஜஹார ஹ৷৷5.31.1৷৷"},{"sloka":"ராஜா தஷரதோ நாம ரதகுஞ்ஜரவாஜிமாந்.புண்யஷீலோ மஹாகீர்திரிக்ஷ்வாகூணாஂ மஹாயஷாஃ৷৷5.31.2৷৷"},{"sloka":"ராஜர்ஷீணாஂ குணஷ்ரேஷ்டஸ்தபஸா சர்ஷிபி ஸ்ஸமஃ.சக்ரவர்திகுலே ஜாதஃ புரந்தரஸமோ பலே৷৷5.31.3৷৷"},{"sloka":"அஹிஂஸாரதிரக்ஷுத்ரோ கரிணீ ஸத்யபராக்ரமஃ.முக்யஷ்சேக்ஷ்வாகுவஂஷஸ்ய லக்ஷ்மீவாந் லக்ஷ்மிவர்தநஃ৷৷5.31.4৷৷"},{"sloka":"பார்திவவ்யஞ்ஜநைர்யுக்தஃ பரிதுஷ்ரீஃ பார்திவர்ஷபஃ.பரிதிவ்யாஂ சதுரந்தாயாஂ விஷ்ருதஸ்ஸுகதஸ்ஸுகீ৷৷5.31.5৷৷"},{"sloka":"தஸ்ய புத்ரஃ ப்ரியோ ஜ்யேஷ்டஸ்தாராதிபநிபாநநஃ.ராமோ நாம விஷேஷஜ்ஞஃ ஷ்ரேஷ்ட ஸ்ஸர்வதநுஷ்மதாம்৷৷5.31.6৷৷"},{"sloka":"ரக்ஷிதா ஸ்வஸ்ய தர்மஸ்ய ஸ்வஜநஸ்ய ச ரக்ஷிதா.ரக்ஷிதா ஜீவலோகஸ்ய தர்மஸ்ய ச பரந்தபஃ৷৷5.31.7৷৷"},{"sloka":"தஸ்ய ஸத்யாபிஸந்தஸ்ய வரித்தஸ்ய வசநாத்பிதுஃ.ஸபார்யஸ்ஸஹ ச ப்ராத்ரா வீரஃ ப்ரவ்ராஜிதோ வநம்৷৷5.31.8৷৷"},{"sloka":"தேந தத்ர மஹாரண்யே மரிகயாஂ பரிதாவதா.ராக்ஷஸா நிஹதாஷ்ஷூரா பஹவஃ காமரூபிணஃ৷৷5.31.9৷৷"},{"sloka":"ஜநஸ்தாநவதஂ ஷ்ருத்வா ஹதௌ ச கரதூஷணௌ.ததஸ்த்வமர்ஷாபஹரிதா ஜாநகீ ராவணேந து৷৷5.31.10৷৷வஞ்சயித்வா வநே ராமஂ மரிகரூபேண மாயயா."},{"sloka":"ஸ மார்கமாணஸ்தாஂ தேவீஂ ராமஸ்ஸீதாமநிந்திதாம்৷৷5.31.11৷৷ஆஸஸாத வநே மித்ரஂ ஸுக்ரீவஂ நாம வாநரம்."},{"sloka":"தத ஸ்ஸ வாலிநஂ ஹத்வா ராமஃ பரபுரஞ்ஜயஃ৷৷5.31.12৷৷ப்ராயச்சத்கபிராஜ்யஂ தத்ஸுக்ரீவாய மஹாபலஃ."},{"sloka":"ஸுக்ரீவேணாபி ஸந்திஷ்டா ஹரயஃ காமரூபிணஃ৷৷5.31.13৷৷திக்ஷு ஸர்வாஸு தாஂ தேவீஂ விசிந்வந்தி ஸஹஸ்ரஷஃ."},{"sloka":"அஹஂ ஸம்பாதிவசநாச்சதயோஜநமாயதம்৷৷5.31.14৷৷அஸ்யா ஹேதோர்விஷாலாக்ஷ்யாஃ ஸாகரஂ வேகவாந்ப்லுதஃ."},{"sloka":"யதாரூபாஂ யதாவர்ணாஂ யதாலக்ஷ்மீவதீஂ ச நிஷ்சிதாம்৷৷5.31.15৷৷அஷ்ரௌஷஂ ராகவஸ்யாஹஂ ஸேயமாஸாதிதா மயா."},{"sloka":"விரராமைவமுக்த்வாஸௌ வாசஂ வாநரபுங்கவஃ৷৷5.31.16৷৷ஜாநகீ சாபி தச்ச்ருத்வா பரஂ விஸ்மயமாகதா."},{"sloka":"ததஸ்ஸா வக்ரகேஷாந்தா ஸுகேஷீ கேஷஸஂவரிதம்৷৷5.31.17৷৷உந்நம்ய வதநஂ பீருஷ்ஷிஂஷுபாவரிக்ஷமைக்ஷத."},{"sloka":"நிஷம்ய ஸீதா வசநஂ கபேஷ்ச திஷஷ்ச ஸர்வாஃ ப்ரதிஷஷ்ச வீக்ஷ்ய.ஸ்வயஂ ப்ரஹர்ஷஂ பரமஂ ஜகாம ஸர்வாத்மநா ராமமநுஸ்மரந்தீ ৷৷5.31.18৷৷"},{"sloka":"ஸா திர்யகூர்த்வஂ ச ததாப்யதஸ்தாந்நிரீக்ஷமாணா தமசிந்த்யபுத்திம்.ததர்ஷ பிங்காதிபதேரமாத்யஂ வாதாத்மஜஂ ஸூர்யமிவோதயஸ்தம்৷৷5.31.19৷৷"}]