[{"sloka":"[Sugriva's anxiety to know the reason for Lakshmana's anger --- Hanuman persuades Sugriva to act.]அங்கதஸ்ய வசஷ்ஷ்ருத்வா ஸுக்ரீவஸ்ஸசிவைஸ்ஸஹ.லக்ஷ்மணஂ குபிதஂ ஷ்ருத்வா முமோசாஸநமாத்மவாந்4.32.1৷৷"},{"sloka":"ஸசிவாநப்ரவீத்வாக்யஂ நிஷ்சித்ய குருலாகவம்.மந்த்ரஜ்ஞாந்மந்த்ரகுஷலோ மந்த்ரேஷு பரிநிஷ்டிதாந்4.32.2৷৷"},{"sloka":"ந மே துர்வ்யாஹரிதஂ கிஞ்சிந்நாபி மே துரநுஷ்டிதம்.லக்ஷ்மணோ ராகவப்ராதா க்ருத்தஃ கிமிதி சிந்தயே4.32.3৷৷"},{"sloka":"அஸுஹரித்பிர்மமாமித்ரைர்நித்யமந்தரதர்ஷிபிஃ.மம தோஷாநஸம்பூதாந் ஷ்ராவிதோ ராகவாநுஜஃ4.32.4৷৷"},{"sloka":"அத்ர தாவத்யதாபுத்தி ஸர்வைரேவ யதாவிதி.பாவஸ்ய நிஷ்சயஸ்தாவத்விஜ்ஞேயோ நிபுணஂ ஷநைஃ4.32.5৷৷"},{"sloka":"ந கல்வஸ்தி மம த்ராஸோ லக்ஷ்மணாந்நாபி ராகவாத்.மித்ரஂ த்வஸ்தாநகுபிதஂ ஜநயத்யேவ ஸம்ப்ரமம்4.32.6৷৷"},{"sloka":"ஸர்வதா ஸுகரஂ மித்ரஂ துஷ்கரஂ பரிபாலநம்.அநித்யத்வாச்ச சித்தாநாஂ ப்ரீதிரல்பேபி பித்யதே4.32.7৷৷"},{"sloka":"அதோ நிமித்தஂ த்ரஸ்தோஹஂ ராமேண து மஹாத்மநா.யந்மயோபகரிதஂ ஷக்யஂ ப்ரதிகர்துஂ ந தந்மயா4.32.8৷৷"},{"sloka":"ஸுக்ரீவேணைவமுக்தஸ்து ஹநுமாந்ஹரிபுங்கவஃ.உவாச ஸ்வேந தர்கேண மத்யே வாநரமந்த்ரிணாம்4.32.9৷৷"},{"sloka":"ஸர்வதா நைததாஷ்சர்யஂ யஸ்த்வஂ ஹரிகணேஷ்வர!.ந விஸ்மரஸி ஸுஸ்நிக்தமுபகார கரிதஂ ஷுபம்4.32.10৷৷"},{"sloka":"ராகவேண து வீரேண பயமுத்ஸரிஜ்ய தூரதஃ.த்வத்ப்ரியார்தஂ ஹதோ வாலீ ஷக்ரதுல்யபராக்ரமஃ4.32.11৷৷"},{"sloka":"ஸர்வதா ப்ரணயாத்கரித்தோ ராகவோ நாத்ர ஸஂஷயஃ.ப்ராதரஂ ஸம்ப்ரஹிதவாந்லக்ஷ்மணஂ லக்ஷ்மிவர்தநம்4.32.12৷৷"},{"sloka":"த்வஂ ப்ரமத்தோ ந ஜாநீஷே காலஂ காலவிதாஂ வர.புல்லஸப்தச்சதஷ்யாமா ப்ரவரித்தா து ஷரச்சிவா4.32.13৷৷"},{"sloka":"நிர்மலக்ரஹநக்ஷத்ரா த்யௌஃ ப்ரநஷ்டவலாஹகா.ப்ரஸந்நாஷ்ச திஷஸ்ஸர்வாஸ்ஸரிதஷ்ச ஸராஂஸி ச4.32.14৷৷"},{"sloka":"ப்ராப்தமுத்யோககாலஂ து நாவைஷி ஹரிபுங்கவ.த்வஂ ப்ரமத்த இதி வ்யக்தஂ லக்ஷ்மணோயமிஹாகதஃ4.32.15৷৷"},{"sloka":"ஆர்தஸ்ய ஹரிததாரஸ்ய புருஷஂ புருஷாந்தராத்.வசநஂ மர்ஷணீயஂ தே ராகவஸ்ய மஹாத்மநஃ4.32.16৷৷"},{"sloka":"கரிதாபராதஸ்ய ஹி தே நாந்யத்பஷ்யாம்யஹஂ க்ஷமம்.அந்தரேணாஞ்ஜலிஂ பத்த்வா லக்ஷ்மணஸ்ய ப்ரஸாதநாத்4.32.17৷৷"},{"sloka":"நியுக்தைர்மந்த்ரிபிர்வாச்யோ ஹ்யவஷ்யஂ பார்திவோ ஹிதம்.அத ஏவ பயஂ த்யக்த்வா ப்ரவீம்யவதரிதஂ வசஃ4.32.18৷৷"},{"sloka":"அபிக்ருத்தஸ்ஸமர்தோ ஹி சாபமுத்யம்ய ராகவஃ.ஸதேவாஸுரகந்தர்வஂ வஷே ஸ்தாபயிதுஂ ஜகத்4.32.19৷৷"},{"sloka":"ந ஸ க்ஷமஃ கோபயிதுஂ யஃ ப்ரஸாத்யஃ புநர்பவேத்.பூர்வோபகாரஂ ஸ்மரதா கரிதஜ்ஞேந விஷேஷதஃ4.32.20৷৷"},{"sloka":"தஸ்ய மூர்த்நா ப்ரணம்ய த்வஂ ஸபுத்ரஸ்ஸஸுஹரிஜ்ஜநஃ.ராஜஂஸ்திஷ்டஸ்வ ஸமயே பர்துர்பார்யேவ தத்வஷஃ4.32.21৷৷"},{"sloka":"ந ராமராமாநுஜஷாஸநஂ த்வயாகபீந்த்ர! யுக்தஂ மநஸாப்யபோஹிதும்.மநோ ஹி தே ஜ்ஞாஸ்யதி மாநுஷஂ பலஂஸ ராகவஸ்யாஸ்ய ஸுரேந்த்ரவர்சஸஃ4.32.22৷৷"}]